cli/__init__.py
cli/commands.py
domain/__init__.py
domain/product.py
domain/protocol.py
infrastructure/__init__.py
infrastructure/factory.py
infrastructure/json_backend.py
tests/__init__.py
tests/test_json_backend.py
warehouse_cli-0.2.1.dist-info/METADATA
warehouse_cli-0.2.1.dist-info/WHEEL
warehouse_cli-0.2.1.dist-info/entry_points.txt
warehouse_cli-0.2.1.dist-info/top_level.txt
warehouse_cli-0.2.1.dist-info/RECORD
